Workbook
Name aporte: APP!$D$12
Name patrimonio: APP!$D$15
Name qtd_anos: APP!$D$13
Name rendimento_carteira: APP!$D$8
Name salario: APP!$D$7
Name sugestao_investimento: APP!$D$9
Name Taxa_mensal: APP!$D$14

Sheet APP
B6: CONFIGURAÇÕES
B7: Salário | D7: 2000
B8: Rendimento carteira | D8: 0.006
B9: Sugestão Investimento (30%) | D9: =salario*(30/100) -> 600
B11: INVESTIMENTO MENSAL
B12: Quanto investir por mês? | D12: 200
B13: Por quantos anos devo investir? | D13: 5
B14: Qual taxa rendimento mensal? | D14: 0.01079
B15: Qual patrimônio acumulado terei? | D15: =FV(Taxa_mensal,qtd_anos*12,aporte)*-1 -> 16755.383
B16: Valor dos dividendos mensais? | D16: =patrimonio*rendimento_carteira -> 100.5323
B18: CENÁRIOS | D18: Dividendo
B19: Quanto em 2 anos? | C19: =FV($D$14,MID(B19,11,2)*12,$D$12)*-1 -> 5445.5255 | D19: =C19*rendimento_carteira -> 32.673153
B20: Quanto em 5 anos? | C20: =FV($D$14,MID(B20,11,2)*12,$D$12)*-1 -> 16755.383 | D20: =C20*rendimento_carteira -> 100.5323
B21: Quanto em 10 anos? | C21: =FV($D$14,MID(B21,11,2)*12,$D$12)*-1 -> 48656.843 | D21: =C21*rendimento_carteira -> 291.94106
B22: Quanto em 20 anos? | C22: =FV($D$14,MID(B22,11,2)*12,$D$12)*-1 -> 225039.68 | D22: =C22*rendimento_carteira -> 1350.2381
B23: Quanto em 30 anos? | C23: =FV($D$14,MID(B23,11,2)*12,$D$12)*-1 -> 864433.93 | D23: =C23*rendimento_carteira -> 5186.6036
B25: PERFIL | C25: AGRESSIVO
B26: Valor a ser investido por Mês | C26: =aporte -> 200
B28: Tipo de FII | C28: Percentual Sugerido | D28: Valores
B29: PAPEL | C29: =VLOOKUP(CONCATENATE($C$25,"-",B29),bd!A:D,4,0) -> 0.5 | D29: =C29*aporte -> 100
B30: TIJOLO | C30: =VLOOKUP(CONCATENATE($C$25,"-",B30),bd!A:D,4,0) -> 0.1 | D30: =C30*aporte -> 20
B31: HÍBRIDOS | C31: =VLOOKUP(CONCATENATE($C$25,"-",B31),bd!A:D,4,0) -> 0.05 | D31: =C31*aporte -> 10
B32: FOFs | C32: =VLOOKUP(CONCATENATE($C$25,"-",B32),bd!A:D,4,0) -> 0.05 | D32: =C32*aporte -> 10
B33: DESENVOLVIMENTO | C33: =VLOOKUP(CONCATENATE($C$25,"-",B33),bd!A:D,4,0) -> 0.2 | D33: =C33*aporte -> 40
B34: HOTELARIAS | C34: =VLOOKUP(CONCATENATE($C$25,"-",B34),bd!A:D,4,0) -> 0.1 | D34: =C34*aporte -> 20
D35: =SUM(D29:D34) -> 200

Sheet bd
A1: CP | B1: PERFIL | C1: Tipo_FII | D1: percent
A2: CONSERVADOR-PAPEL | B2: CONSERVADOR | C2: PAPEL | D2: 0.3
A3: CONSERVADOR-TIJOLO | B3: CONSERVADOR | C3: TIJOLO | D3: 0.5
A4: CONSERVADOR-HÍBRIDOS | B4: CONSERVADOR | C4: HÍBRIDOS | D4: 0.1
A5: CONSERVADOR-FOFs | B5: CONSERVADOR | C5: FOFs | D5: 0.1
A6: CONSERVADOR-DESENVOLVIMENTO | B6: CONSERVADOR | C6: DESENVOLVIMENTO | D6: 0
A7: CONSERVADOR-HOTELARIAS | B7: CONSERVADOR | C7: HOTELARIAS | D7: 0
A8: MODERADO-PAPEL | B8: MODERADO | C8: PAPEL | D8: 0.32
A9: MODERADO-TIJOLO | B9: MODERADO | C9: TIJOLO | D9: 0.35
A10: MODERADO-HÍBRIDOS | B10: MODERADO | C10: HÍBRIDOS | D10: 0.08
A11: MODERADO-FOFs | B11: MODERADO | C11: FOFs | D11: 0.05
A12: MODERADO-DESENVOLVIMENTO | B12: MODERADO | C12: DESENVOLVIMENTO | D12: 0.1
A13: MODERADO-HOTELARIAS | B13: MODERADO | C13: HOTELARIAS | D13: 0.1
... A19: AGRESSIVO-HOTELARIAS | B19: AGRESSIVO | C19: HOTELARIAS | D19: 0.1
